RBGeneratorCpp.cp313-win_amd64.pyd
rb_generator/__init__.py
rb_generator-0.0.5.dist-info/LICENSE
rb_generator-0.0.5.dist-info/METADATA
rb_generator-0.0.5.dist-info/WHEEL
rb_generator-0.0.5.dist-info/top_level.txt
rb_generator-0.0.5.dist-info/RECORD
